bibtex_updater/__init__.py
bibtex_updater/_version.py
bibtex_updater/fact_checker.py
bibtex_updater/filter.py
bibtex_updater/obsidian_keywords.py
bibtex_updater/updater.py
bibtex_updater/utils.py
bibtex_updater/zotero.py
bibtex_updater/zotero_sync.py
bibtex_updater/cli/__init__.py
bibtex_updater/cli/fact_checker_cli.py
bibtex_updater/cli/filter_cli.py
bibtex_updater/cli/obsidian_keywords_cli.py
bibtex_updater/cli/updater_cli.py
bibtex_updater/cli/zotero_cli.py
bibtex_updater/cli/zotero_organizer_cli.py
bibtex_updater/organizer/__init__.py
bibtex_updater/organizer/cache.py
bibtex_updater/organizer/classifier.py
bibtex_updater/organizer/collection_manager.py
bibtex_updater/organizer/config.py
bibtex_updater/organizer/main.py
bibtex_updater/organizer/taxonomy.py
bibtex_updater/organizer/backends/__init__.py
bibtex_updater/organizer/backends/base.py
bibtex_updater/organizer/backends/claude_backend.py
bibtex_updater/organizer/backends/embedding_backend.py
bibtex_updater/organizer/backends/openai_backend.py
bibtex_updater-0.4.1.dist-info/METADATA
bibtex_updater-0.4.1.dist-info/WHEEL
bibtex_updater-0.4.1.dist-info/entry_points.txt
bibtex_updater-0.4.1.dist-info/licenses/LICENSE
bibtex_updater-0.4.1.dist-info/RECORD
