Metadata-Version: 2.4
Name: bibtex-updater
Version: 0.4.1
Summary: Replace preprint BibTeX entries with published versions and validate bibliography references
Project-URL: Homepage, https://github.com/rpatrik96/bibtexupdater
Project-URL: Documentation, https://github.com/rpatrik96/bibtexupdater#readme
Project-URL: Repository, https://github.com/rpatrik96/bibtexupdater.git
Project-URL: Issues, https://github.com/rpatrik96/bibtexupdater/issues
Project-URL: Changelog, https://github.com/rpatrik96/bibtexupdater/blob/main/CHANGELOG.md
Author: Patrik Reizinger
License: MIT
License-File: LICENSE
Keywords: academic,arxiv,bibliography,bibtex,citation,crossref,latex,preprint,research
Classifier: Development Status :: 4 - Beta
Classifier: Environment :: Console
Classifier: Intended Audience :: Science/Research
Classifier: License :: OSI Approved :: MIT License
Classifier: Operating System :: OS Independent
Classifier: Programming Language :: Python :: 3
Classifier: Programming Language :: Python :: 3.10
Classifier: Programming Language :: Python :: 3.11
Classifier: Programming Language :: Python :: 3.12
Classifier: Programming Language :: Python :: 3.13
Classifier: Topic :: Scientific/Engineering
Classifier: Topic :: Text Processing :: Markup :: LaTeX
Classifier: Typing :: Typed
Requires-Python: >=3.10
Requires-Dist: bibtexparser>=1.4.0
Requires-Dist: crossref-commons>=0.0.7
Requires-Dist: httpx>=0.24.0
Requires-Dist: rapidfuzz>=3.0.0
Requires-Dist: requests>=2.28.0
Provides-Extra: all
Requires-Dist: pyyaml>=6.0; extra == 'all'
Requires-Dist: pyzotero>=1.5.0; extra == 'all'
Requires-Dist: scholarly>=1.7.0; extra == 'all'
Requires-Dist: sentence-transformers>=2.2.0; extra == 'all'
Provides-Extra: dev
Requires-Dist: black>=24.0.0; extra == 'dev'
Requires-Dist: build>=1.0.0; extra == 'dev'
Requires-Dist: mypy>=1.13.0; extra == 'dev'
Requires-Dist: pre-commit>=3.6.0; extra == 'dev'
Requires-Dist: pytest-cov>=4.0.0; extra == 'dev'
Requires-Dist: pytest>=8.0.0; extra == 'dev'
Requires-Dist: ruff>=0.7.0; extra == 'dev'
Requires-Dist: twine>=5.0.0; extra == 'dev'
Requires-Dist: types-requests>=2.31.0; extra == 'dev'
Provides-Extra: organizer
Requires-Dist: pyyaml>=6.0; extra == 'organizer'
Requires-Dist: pyzotero>=1.5.0; extra == 'organizer'
Provides-Extra: organizer-claude
Requires-Dist: pyyaml>=6.0; extra == 'organizer-claude'
Requires-Dist: pyzotero>=1.5.0; extra == 'organizer-claude'
Provides-Extra: organizer-embedding
Requires-Dist: pyyaml>=6.0; extra == 'organizer-embedding'
Requires-Dist: pyzotero>=1.5.0; extra == 'organizer-embedding'
Requires-Dist: sentence-transformers>=2.2.0; extra == 'organizer-embedding'
Provides-Extra: organizer-openai
Requires-Dist: pyyaml>=6.0; extra == 'organizer-openai'
Requires-Dist: pyzotero>=1.5.0; extra == 'organizer-openai'
Provides-Extra: scholarly
Requires-Dist: scholarly>=1.7.0; extra == 'scholarly'
Provides-Extra: zotero
Requires-Dist: pyzotero>=1.5.0; extra == 'zotero'
